MANIFEST.in
README.md
VERSION
setup.py
golive_django_openapi/__init__.py
golive_django_openapi/tests.py
golive_django_openapi.egg-info/PKG-INFO
golive_django_openapi.egg-info/SOURCES.txt
golive_django_openapi.egg-info/dependency_links.txt
golive_django_openapi.egg-info/requires.txt
golive_django_openapi.egg-info/top_level.txt
golive_django_openapi/openapi/__init__.py
golive_django_openapi/openapi/base.py
golive_django_openapi/openapi/exceptions.py
golive_django_openapi/openapi/method_processor.py
golive_django_openapi/openapi/openapi_gen.py
golive_django_openapi/openapi/pdm_fields.py
golive_django_openapi/openapi/django/__init__.py
golive_django_openapi/openapi/django/fields.py
golive_django_openapi/openapi/django/model.py
golive_django_openapi/openapi/django/model_pdm.py
golive_django_openapi/openapi/django/model_pdm_meta/__init__.py
golive_django_openapi/openapi/django/model_pdm_meta/base.py
golive_django_openapi/openapi/django/model_pdm_meta/config.py
golive_django_openapi/openapi/django/model_pdm_meta/convert.py
golive_django_openapi/openapi/django/model_pdm_meta/getter.py
golive_django_openapi/openapi/django/model_pdm_meta/prop.py
golive_django_openapi/openapi/django/model_pdm_meta/prop_plugins.py
golive_django_openapi/openapi/django/model_pdm_meta/setter.py
golive_django_openapi/openapi/models/__init__.py
golive_django_openapi/openapi/models/base.py
golive_django_openapi/openapi/models/getter_switch.py
golive_django_openapi/openapi/models/pagination.py
golive_django_openapi/openapi/models/shortcuts.py
golive_django_openapi/status_machine/__init__.py
golive_django_openapi/status_machine/base.py
golive_django_openapi/status_machine/exceptions.py
golive_django_openapi/status_machine/export.py
golive_django_openapi/status_machine/status_machine.py
golive_django_openapi/utils/__init__.py
golive_django_openapi/utils/apscheduler_utils.py
golive_django_openapi/utils/cls_utils.py
golive_django_openapi/utils/const.py
golive_django_openapi/utils/decorators.py
golive_django_openapi/utils/dict_utils.py
golive_django_openapi/utils/dt_utils.py
golive_django_openapi/utils/ensured_dict.py
golive_django_openapi/utils/expiring_set.py
golive_django_openapi/utils/extensive_raw_qs.py
