Metadata-Version: 2.1
Name: golive-django-openapi
Version: 0.5.10
Summary: 青橄榄Django OpenAPI框架
Home-page: https://jh-golive-gitlab.goliveplus.cn/golive-project-manage/golive-django-openapi
Author: fk
Author-email: fkfkbill@gmail.com
Classifier: Operating System :: OS Independent
Classifier: Programming Language :: Python
Classifier: Programming Language :: Python :: 3
Requires-Python: >=3.11
Requires-Dist: pydantic<2
Requires-Dist: fastapi<2
Requires-Dist: django
Requires-Dist: django-comment-migrate==0.1.5
Requires-Dist: loguru
Requires-Dist: apscheduler
Requires-Dist: schema
